{
    "floors" : [
        {
            "name": "Groundfloor",
            "nr": "1",
            "uri": "/floor/1",
            "rooms" : [
                {
                    "name": "Kitchen",
                    "nr": "1",
                    "x": "0",
                    "y": "0",
                    "width":"100",
                    "height":"100"
                },
                {
                    "name": "Living room",
                    "nr": "2",
                    "x": "0",
                    "y": "100",
                    "width":"100",
                    "height":"150"
                },
                {
                    "name": "Toilet",
                    "nr": "3",
                    "x": "0",
                    "y": "200",
                    "width":"100",
                    "height":"80"
                },
                {
                    "name": "Hall",
                    "nr": "4",
                    "x": "200",
                    "y": "0",
                    "width":"300",
                    "height":"300"
                },
                {
                    "name": "Dining room",
                    "nr": "5",
                    "x": "300",
                    "y": "300",
                    "width":"200",
                    "height":"200"
                }
            ]
        },
        {
            "name": "First floor",
            "nr": "2",
            "uri": "/floor/2",
            "rooms" : [
                {
                    "name": "Bed room 1",
                    "nr": "6",
                    "x": "0",
                    "y": "0",
                    "width":"100",
                    "height":"100"
                },
                {
                    "name": "Bed room 2",
                    "nr": "7",
                    "x": "200",
                    "y": "0",
                    "width":"100",
                    "height":"100"
                },
                {
                    "name": "Bed room 3",
                    "nr": "8",
                    "x": "0",
                    "y": "200",
                    "width":"100",
                    "height":"100"
                },
                {
                    "name": "Bathroom",
                    "nr": "9",
                    "x": "300",
                    "y": "300",
                    "width":"100",
                    "height":"100"
                }
            ]
        }
    ]
}